leetcode_study_tool/__init__.py
leetcode_study_tool/cli.py
leetcode_study_tool/creator.py
leetcode_study_tool/formatters.py
leetcode_study_tool/graphql.py
leetcode_study_tool/leetcode_to_neetcode.py
leetcode_study_tool/outputs.py
leetcode_study_tool/presets.py
leetcode_study_tool/queries.py
leetcode_study_tool/templates/anki.html.j2
leetcode_study_tool-1.3.5.dist-info/LICENSE.txt
leetcode_study_tool-1.3.5.dist-info/METADATA
leetcode_study_tool-1.3.5.dist-info/WHEEL
leetcode_study_tool-1.3.5.dist-info/entry_points.txt
leetcode_study_tool-1.3.5.dist-info/top_level.txt
leetcode_study_tool-1.3.5.dist-info/RECORD
