Metadata-Version: 2.2
Name: leetcode-study-tool
Version: 1.3.5
Summary: A tool for studying Leetcode with Python
Author-email: John Sutor <johnsutor3@gmail.com>
License: MIT License
Project-URL: homepage, https://github.com/johnsutor/leetcode-study-tool
Project-URL: repository, https://github.com/johnsutor/leetcode-study-tool
Project-URL: changelog, https://github.com/johnsutor/leetcode-study-tool/blob/main/CHANGELOG.md
Keywords: leetcode,leet,study,Anki
Classifier: Development Status :: 5 - Production/Stable
Classifier: Operating System :: Microsoft :: Windows
Classifier: Operating System :: MacOS
Classifier: Operating System :: POSIX :: Linux
Classifier: Programming Language :: Python :: 3.8
Classifier: Programming Language :: Python :: 3.9
Classifier: Programming Language :: Python :: 3.10
Classifier: Programming Language :: Python :: 3.11
Classifier: Programming Language :: Python :: 3.12
Classifier: Programming Language :: Python :: 3.13
Classifier: License :: OSI Approved :: MIT License
Classifier: Topic :: Software Development
Classifier: Topic :: Education
License-File: LICENSE.txt
Requires-Dist: requests==2.32.3
Requires-Dist: XlsxWriter==3.2.0
Requires-Dist: p-tqdm==1.4.2
Requires-Dist: Jinja2==3.1.5
Provides-Extra: dev
Requires-Dist: ruff==0.8.6; extra == "dev"
Requires-Dist: mypy==1.14.1; extra == "dev"
Requires-Dist: types-requests>=2.32.0; extra == "dev"
Requires-Dist: google-api-python-client==2.157.0; extra == "dev"
Requires-Dist: pytest==8.3.4; extra == "dev"
Requires-Dist: pytest-cov>=5.0.0; extra == "dev"
